setup.py
./__init__.py
./connection.py
./docs.py
./fields.py
./settings.py
./apis/__init__.py
./apis/core.py
./apis/route53.py
./apis/sqs.py
./apis/templates/__init__.py
./apis/templates/route53.py
gae_boto.egg-info/PKG-INFO
gae_boto.egg-info/SOURCES.txt
gae_boto.egg-info/dependency_links.txt
gae_boto.egg-info/requires.txt
gae_boto.egg-info/top_level.txt