Metadata-Version: 1.0
Name: gae-boto
Version: 13.10.1
Summary: A recreation of Amazon Boto library that is is compatible with Google App Engine and easier to use.
Home-page: https://github.com/pizzapanther/gae_boto
Author: Paul Bailey
Author-email: paul.m.bailey@gmail.com
License: BSD
Platform: UNKNOWN
